pythonrunscript/__init__.py
pythonrunscript/__main__.py
pythonrunscript/pythonrunscript.py
pythonrunscript-0.2.0.dist-info/LICENSE
pythonrunscript-0.2.0.dist-info/METADATA
pythonrunscript-0.2.0.dist-info/WHEEL
pythonrunscript-0.2.0.dist-info/entry_points.txt
pythonrunscript-0.2.0.dist-info/top_level.txt
pythonrunscript-0.2.0.dist-info/RECORD
