Metadata-Version: 2.1
Name: pythonrunscript
Version: 0.2.0
Summary: pythonrunscript runs scripts installing their dependencies in cached, isolated environments.
Author-email: Alexis Gallagher <alexis@alexisgallagher.com>
License: MIT License
Project-URL: Homepage, https://github.com/AnswerDotAI/pythonrunscript
Project-URL: Issues, https://github.com/AnswerDotAI/pythonrunscript/issues
Keywords: scripting
Classifier: Development Status :: 4 - Beta
Classifier: Intended Audience :: Developers
Classifier: Programming Language :: Python :: 3
Classifier: License :: OSI Approved :: MIT License
Classifier: Operating System :: MacOS
Classifier: Operating System :: POSIX :: Linux
Requires-Python: >=3.9.6
License-File: LICENSE
Provides-Extra: dev
Requires-Dist: pytest ; extra == 'dev'
Requires-Dist: tomlkit ; extra == 'dev'
